ovos_microphone_plugin_socket/__init__.py
ovos_microphone_plugin_socket/version.py
ovos_microphone_plugin_socket-0.0.0a2.dist-info/LICENSE
ovos_microphone_plugin_socket-0.0.0a2.dist-info/METADATA
ovos_microphone_plugin_socket-0.0.0a2.dist-info/WHEEL
ovos_microphone_plugin_socket-0.0.0a2.dist-info/entry_points.txt
ovos_microphone_plugin_socket-0.0.0a2.dist-info/top_level.txt
ovos_microphone_plugin_socket-0.0.0a2.dist-info/zip-safe
ovos_microphone_plugin_socket-0.0.0a2.dist-info/RECORD
